{"inkVersion":21,"root":[["^Ei, você sabe o que significa <color=#008ffc>rhtasf</color> ? ","#","^character:character ","/#","#","^name:Garotinha","/#","\n","ev","str","^Não, o que significa?","/str","/ev",{"*":"0.c-0","flg":20},"ev","str","^Não tenho tempo para isso agora...","/str","/ev",{"*":"0.c-1","flg":20},{"c-0":["\n","^Significa Paz, Amor e Carinho! Eu inventei essa palavra agora.","\n",{"->":"0.g-0"},{"#f":5}],"c-1":["\n",{"->":"0.g-0"},{"#f":5}],"g-0":["done",{"#f":5}]}],"done",{"#f":1}],"listDefs":{}}